Metadata-Version: 2.1
Name: solidity-unfolder
Version: 1.0.1
Summary: A Python package to unfold soldity code with imports into a single file.
Home-page: https://github.com/Jy-Liu/solidity-unfolder
Author: Jun-You Liu
Author-email: junyouliu9@gmail.com
License: MIT
Keywords: soldity solidity-unfolder solidity-flattener               smart-contracts ethereum
Platform: UNKNOWN
Classifier: Development Status :: 3 - Alpha
Classifier: Intended Audience :: Developers
Classifier: License :: OSI Approved :: MIT License
Classifier: Programming Language :: Python :: 3
Classifier: Programming Language :: Python :: 3.4
Classifier: Programming Language :: Python :: 3.5
Classifier: Programming Language :: Python :: 3.6
Classifier: Topic :: Software Development :: Code Generators
Classifier: Topic :: Software Development :: Libraries :: Python Modules
Requires-Python: >=3
